MANIFEST.in
README.md
setup.py
typed/__init__.py
typed.egg-info/PKG-INFO
typed.egg-info/SOURCES.txt
typed.egg-info/dependency_links.txt
typed.egg-info/top_level.txt