Metadata-Version: 1.0
Name: typed
Version: 0.1
Summary: A Python typing library for data validation.
Home-page: http://github.com/zemanta/typed/
Author: Tom Primozic
Author-email: tom.primozic@zemanta.com
License: UNKNOWN
Platform: UNKNOWN
